py_rpc/__init__.py
py_rpc-1.0.0.dist-info/METADATA
py_rpc-1.0.0.dist-info/WHEEL
py_rpc-1.0.0.dist-info/top_level.txt
py_rpc-1.0.0.dist-info/RECORD
