Metadata-Version: 2.1
Name: py-rpc
Version: 1.0.0
Summary: A simple and external rpc framework.
Home-page: UNKNOWN
Author: ZhangDong
Author-email: 785576549@qq.com
License: MIT
Platform: UNKNOWN
Classifier: Development Status :: 3 - Alpha
Classifier: Intended Audience :: Developers
Classifier: Topic :: Software Development :: Build Tools
Classifier: License :: OSI Approved :: MIT License
Classifier: Programming Language :: Python :: 3
Classifier: Operating System :: OS Independent
Requires-Dist: gevent
